padacioso/__init__.py
padacioso/bracket_expansion.py
padacioso/opm.py
padacioso/version.py
padacioso-1.0.0.dist-info/LICENSE.md
padacioso-1.0.0.dist-info/METADATA
padacioso-1.0.0.dist-info/WHEEL
padacioso-1.0.0.dist-info/entry_points.txt
padacioso-1.0.0.dist-info/top_level.txt
padacioso-1.0.0.dist-info/RECORD
